Metadata-Version: 2.1
Name: cmdOS
Version: 1.0.0
Summary: My CMD 模組
Home-page: UNKNOWN
License: LGPL
Platform: UNKNOWN
